systolic_array/systolic_array_sort3.sv
//
// Sort three values into minimum, median, and maximum values
//

module systolic_array_sort3 #(
    parameter KEY_WIDTH=8,
    parameter DATA_WIDTH=32
) (
    input logic [KEY_WIDTH+DATA_WIDTH-1:0] a, 
    input logic [KEY_WIDTH+DATA_WIDTH-1:0] b, 
    input logic [KEY_WIDTH+DATA_WIDTH-1:0] c,
    output logic [KEY_WIDTH+DATA_WIDTH-1:0] minv, medv, maxv
);

  // Some internal used constants
  localparam [KEY_WIDTH+DATA_WIDTH-1:0] PQINF = {{KEY_WIDTH{1'b1}}, {DATA_WIDTH{1'b0}}};
  // localparam [KEY_WIDTH+DATA_WIDTH-1:0] PQNEGINF = '{KEY_WIDTH{1'b0}, DATA_WIDTH{1'b0}};

  logic [KEY_WIDTH-1:0] a_key, b_key, c_key;
  logic a_gt_b, a_gt_c, b_gt_c;

  // extract the keys
  assign a_key = a[KEY_WIDTH+DATA_WIDTH-1:DATA_WIDTH];
  assign b_key = b[KEY_WIDTH+DATA_WIDTH-1:DATA_WIDTH];
  assign c_key = c[KEY_WIDTH+DATA_WIDTH-1:DATA_WIDTH];

  assign a_gt_b = a_key > b_key;
  assign a_gt_c = a_key > c_key;
  assign b_gt_c = b_key > c_key;

  always_comb begin
    case ({a_gt_b, a_gt_c, b_gt_c})
      3'b000 : begin
        minv = a;
        medv = b;
        maxv = c;
      end
      3'b001 : begin
        minv = a;
        medv = c;
        maxv = b;
      end
      3'b100 : begin
        minv = b;
        medv = a;
        maxv = c;
      end
      3'b011 : begin
        minv = c;
        medv = a;
        maxv = b;
      end
      3'b110 : begin
        minv = b;
        medv = c;
        maxv = a;
      end
      3'b111 : begin
        minv = c;
        medv = b;
        maxv = a;
      end
      // default : begin // remaining cases 3'b010, 3'b101 cannot occur! If happened, revoke keys
      //   minv = PQINF;
      //   medv = PQINF;
      //   maxv = PQINF;
      // end
    endcase
  end
endmodule : systolic_array_sort3

systolic_array/systolic_array_sort3_tb.sv
`timescale 1ns/1ps
//
// systolic_pq_sort3_tb: simple stimulus-only testbench for sort3
//

module systolic_array_sort3_tb;
  parameter KEY_WIDTH=8, DATA_WIDTH=4;
  logic [KEY_WIDTH+DATA_WIDTH-1:0] a, b, c;
  logic [KEY_WIDTH+DATA_WIDTH-1:0] minv, medv, maxv;
  systolic_array_sort3 #(.KEY_WIDTH(KEY_WIDTH), .DATA_WIDTH(DATA_WIDTH)) DUV (.a(a), .b(b), .c(c), .minv(minv), .medv(medv), .maxv(maxv));

  initial begin

    $dumpfile("sort3.vcd");
    $dumpvars(0, systolic_array_sort3_tb);

    $monitor("time-%t, a=%h b=%h c = %h | minv=%h medv=%h maxv=%h", $time, a, b, c, minv, medv, maxv);

    a = {{KEY_WIDTH{1'b0}}, {DATA_WIDTH{1'b0}}}; 
    b = {{KEY_WIDTH{1'b0}}, {DATA_WIDTH{1'b0}}}; 
    c = {{KEY_WIDTH{1'b0}}, {DATA_WIDTH{1'b0}}};
    #100;
    
    a = {{KEY_WIDTH{1'b1}}, {DATA_WIDTH{1'b0}}}; 
    b = {{KEY_WIDTH{1'b0}}, {DATA_WIDTH{1'b0}}}; 
    c = {{KEY_WIDTH{1'b0}}, {DATA_WIDTH{1'b0}}};
    #100;

    a = {{KEY_WIDTH{1'b0}}, {DATA_WIDTH{1'b1}}}; 
    b = {{KEY_WIDTH{1'b0}}, {DATA_WIDTH{1'b0}}}; 
    c = {{KEY_WIDTH{1'b0}}, {DATA_WIDTH{1'b0}}};
    #100;

    a = {{KEY_WIDTH{1'b0}}, {DATA_WIDTH{1'b0}}}; 
    b = {{KEY_WIDTH{1'b1}}, {DATA_WIDTH{1'b0}}}; 
    c = {{KEY_WIDTH{1'b0}}, {DATA_WIDTH{1'b0}}};
    #100;

    a = {{KEY_WIDTH{1'b0}}, {DATA_WIDTH{1'b0}}}; 
    b = {{KEY_WIDTH{1'b0}}, {DATA_WIDTH{1'b0}}}; 
    c = {{KEY_WIDTH{1'b0}}, {DATA_WIDTH{1'b0}}};
    #100;

    a = {{KEY_WIDTH{1'b0}}, {DATA_WIDTH{1'b0}}}; 
    b = {{KEY_WIDTH{1'b0}}, {DATA_WIDTH{1'b0}}}; 
    c = {{KEY_WIDTH{1'b1}}, {DATA_WIDTH{1'b0}}};
    #100;

    a = {{KEY_WIDTH{1'b0}}, {DATA_WIDTH{1'b0}}}; 
    b = {{KEY_WIDTH{1'b0}}, {DATA_WIDTH{1'b0}}}; 
    c = {{KEY_WIDTH{1'b0}}, {DATA_WIDTH{1'b1}}};
    #100;

    a = {{KEY_WIDTH{1'b1}}, {DATA_WIDTH{1'b1}}}; 
    b = {{KEY_WIDTH{1'b0}}, {DATA_WIDTH{1'b0}}}; 
    c = {{KEY_WIDTH{1'b0}}, {DATA_WIDTH{1'b0}}};
    #100;

    a = {{KEY_WIDTH{1'b0}}, {DATA_WIDTH{1'b0}}}; 
    b = {{KEY_WIDTH{1'b1}}, {DATA_WIDTH{1'b0}}}; 
    c = {{KEY_WIDTH{1'b0}}, {DATA_WIDTH{1'b0}}};
    #100;

    a = {{KEY_WIDTH{1'b0}}, {DATA_WIDTH{1'b0}}}; 
    b = {{KEY_WIDTH{1'b0}}, {DATA_WIDTH{1'b0}}}; 
    c = {{KEY_WIDTH{1'b1}}, {DATA_WIDTH{1'b0}}};
    #100;

    a = {{KEY_WIDTH{1'b1}}, {DATA_WIDTH{1'b0}}}; 
    b = {{KEY_WIDTH{1'b1}}, {DATA_WIDTH{1'b0}}}; 
    c = {{KEY_WIDTH{1'b0}}, {DATA_WIDTH{1'b0}}};
    #100;

    a = {{KEY_WIDTH{1'b1}}, {DATA_WIDTH{1'b0}}}; 
    b = {{KEY_WIDTH{1'b0}}, {DATA_WIDTH{1'b0}}}; 
    c = {{KEY_WIDTH{1'b1}}, {DATA_WIDTH{1'b0}}};
    #100;

    a = {{KEY_WIDTH{1'b0}}, {DATA_WIDTH{1'b0}}}; 
    b = {{KEY_WIDTH{1'b1}}, {DATA_WIDTH{1'b0}}}; 
    c = {{KEY_WIDTH{1'b1}}, {DATA_WIDTH{1'b0}}};
    #100;

    a = {{KEY_WIDTH{1'b1}}, {DATA_WIDTH{1'b0}}}; 
    b = {{KEY_WIDTH{1'b1}}, {DATA_WIDTH{1'b0}}}; 
    c = {{KEY_WIDTH{1'b0}}, {DATA_WIDTH{1'b0}}};
    #100;

    a = {{KEY_WIDTH{1'b1}}, {DATA_WIDTH{1'b0}}}; 
    b = {{KEY_WIDTH{1'b1}}, {DATA_WIDTH{1'b0}}}; 
    c = {{KEY_WIDTH{1'b0}}, {DATA_WIDTH{1'b0}}};
    #100;

    a = {{KEY_WIDTH{1'b1}}, {DATA_WIDTH{1'b0}}}; 
    b = {{KEY_WIDTH{1'b0}}, {DATA_WIDTH{1'b0}}}; 
    c = {{KEY_WIDTH{1'b1}}, {DATA_WIDTH{1'b0}}};
    #100;

    a = {{KEY_WIDTH{1'b0}}, {DATA_WIDTH{1'b0}}}; 
    b = {{KEY_WIDTH{1'b1}}, {DATA_WIDTH{1'b0}}}; 
    c = {{KEY_WIDTH{1'b1}}, {DATA_WIDTH{1'b0}}};
    #100;

    a = {{KEY_WIDTH{1'b1}}, {DATA_WIDTH{1'b0}}}; 
    b = {{KEY_WIDTH{1'b1}}, {DATA_WIDTH{1'b0}}}; 
    c = {{KEY_WIDTH{1'b0}}, {DATA_WIDTH{1'b0}}};
    #100;

    a = {{KEY_WIDTH{1'b1}}, {DATA_WIDTH{1'b0}}}; 
    b = {{KEY_WIDTH{1'b0}}, {DATA_WIDTH{1'b0}}}; 
    c = {{KEY_WIDTH{1'b1}}, {DATA_WIDTH{1'b0}}};
    #100;

    a = {{KEY_WIDTH{1'b0}}, {DATA_WIDTH{1'b0}}}; 
    b = {{KEY_WIDTH{1'b1}}, {DATA_WIDTH{1'b0}}}; 
    c = {{KEY_WIDTH{1'b1}}, {DATA_WIDTH{1'b0}}};
    #100;

    a = {{KEY_WIDTH{1'b1}}, {DATA_WIDTH{1'b0}}}; 
    b = {{KEY_WIDTH{1'b1}}, {DATA_WIDTH{1'b0}}}; 
    c = {{KEY_WIDTH{1'b1}}, {DATA_WIDTH{1'b0}}};
    #100;

    $stop;

  end

endmodule

systolic_array/sort3.vcd
$date
	Fri Sep  6 23:36:56 2024
$end
$version
	Icarus Verilog
$end
$timescale
	1ps
$end
$scope module systolic_array_sort3_tb $end
$var wire 12 ! minv [11:0] $end
$var wire 12 " medv [11:0] $end
$var wire 12 # maxv [11:0] $end
$var parameter 32 $ DATA_WIDTH $end
$var parameter 32 % KEY_WIDTH $end
$var reg 12 & a [11:0] $end
$var reg 12 ' b [11:0] $end
$var reg 12 ( c [11:0] $end
$scope module DUV $end
$var wire 12 ) a [11:0] $end
$var wire 12 * b [11:0] $end
$var wire 12 + c [11:0] $end
$var wire 8 , c_key [7:0] $end
$var wire 8 - b_key [7:0] $end
$var wire 1 . b_gt_c $end
$var wire 8 / a_key [7:0] $end
$var wire 1 0 a_gt_c $end
$var wire 1 1 a_gt_b $end
$var parameter 32 2 DATA_WIDTH $end
$var parameter 32 3 KEY_WIDTH $end
$var parameter 12 4 PQINF $end
$var reg 12 5 maxv [11:0] $end
$var reg 12 6 medv [11:0] $end
$var reg 12 7 minv [11:0] $end
$upscope $end
$upscope $end
$enddefinitions $end
$comment Show the parameter values. $end
$dumpall
b111111110000 4
b1000 3
b100 2
b1000 %
b100 $
$end
#0
$dumpvars
b0 7
b0 6
b0 5
01
00
b0 /
0.
b0 -
b0 ,
b0 +
b0 *
b0 )
b0 (
b0 '
b0 &
b0 #
b0 "
b0 !
$end
#100000
b111111110000 #
b111111110000 5
11
10
b11111111 /
b111111110000 &
b111111110000 )
#200000
b0 #
b0 5
b1111 !
b1111 7
01
00
b0 /
b1111 &
b1111 )
#300000
b111111110000 #
b111111110000 5
1.
b11111111 -
b0 "
b0 6
b0 !
b0 7
b111111110000 '
b111111110000 *
b0 &
b0 )
#400000
b0 #
b0 5
0.
b0 -
b0 '
b0 *
#500000
b111111110000 #
b111111110000 5
b11111111 ,
b111111110000 (
b111111110000 +
#600000
b1111 #
b1111 5
b0 ,
b1111 (
b1111 +
#700000
b111111111111 #
b111111111111 5
11
10
b11111111 /
b0 (
b0 +
b111111111111 &
b111111111111 )
#800000
1.
b11111111 -
b111111110000 #
b111111110000 5
b0 "
b0 6
01
00
b0 /
b111111110000 '
b111111110000 *
b0 &
b0 )
#900000
b11111111 ,
0.
b0 -
b111111110000 (
b111111110000 +
b0 '
b0 *
#1000000
10
1.
b0 ,
b11111111 -
b111111110000 #
b111111110000 5
b111111110000 "
b111111110000 6
b0 !
b0 7
01
b11111111 /
b0 (
b0 +
b111111110000 '
b111111110000 *
b111111110000 &
b111111110000 )
#1100000
00
b11111111 ,
11
0.
b0 -
b111111110000 (
b111111110000 +
b0 '
b0 *
#1200000
b11111111 -
01
b0 /
b111111110000 '
b111111110000 *
b0 &
b0 )
#1300000
10
1.
b0 ,
b111111110000 #
b111111110000 5
b0 !
b0 7
b11111111 /
b0 (
b0 +
b111111110000 &
b111111110000 )
#1500000
00
b11111111 ,
11
0.
b0 -
b111111110000 (
b111111110000 +
b0 '
b0 *
#1600000
b11111111 -
01
b0 /
b111111110000 '
b111111110000 *
b0 &
b0 )
#1700000
10
1.
b0 ,
b111111110000 #
b111111110000 5
b0 !
b0 7
b11111111 /
b0 (
b0 +
b111111110000 &
b111111110000 )
#1800000
00
b11111111 ,
11
0.
b0 -
b111111110000 (
b111111110000 +
b0 '
b0 *
#1900000
b11111111 -
01
b0 /
b111111110000 '
b111111110000 *
b0 &
b0 )
#2000000
b111111110000 !
b111111110000 7
b11111111 /
b111111110000 &
b111111110000 )
