systolic_array/tmp_open_list_queue.sv
module tmp_open_list_queue #(
  parameter width = 32,
  parameter length = 32
)
(
  input  logic clk,
  input  logic reset,

  input  logic insert,
  input  logic pop,

  input  logic [width-1:0] in_f_value,

  output logic [width-1:0] out_f_value,

  output logic full,
  output logic empty
);

localparam l_bits = $clog2(length);

logic [(l_bits+1):0] next_size, curr_size;

logic [length-1:0][width-1:0] IB, next_IB;
logic [length-1:0][width-1:0] OB, next_OB;

// Valid signals
logic [length-1:0] IB_valid;
logic [length-1:0] next_IB_valid;
logic [length-1:0] OB_valid;
logic [length-1:0] next_OB_valid;

// Comparators
logic [length-1:0] less_then_previous_IB;
logic [length-1:0] less_then_next_IB;
logic [length-1:0] less_then_same_OB;
logic [length-1:0] less_then_next_OB;
logic [length-1:0] less_then_next_next_OB;

assign full      = next_size == length;
assign empty     = next_size == '0;

integer i, j;

assign out_f_value = OB[0];

always_comb begin
  // defaults
  next_IB = '1;
  next_OB = OB;
  next_IB_valid = '0;
  next_OB_valid = OB_valid;
  next_size = curr_size;

  if (insert && pop) begin
    next_size = curr_size;
    if ((in_f_value < OB[0]) && (in_f_value < OB[1]) && (!IB_valid[0] || (in_f_value < IB[0]))) begin
      // enqueue directly into outQueue[0]
      next_OB[0] = in_f_value;
      next_OB_valid[0] = 1;
    end else begin
      // enqueue into inQueue[0]
      next_IB[0] = in_f_value;
      next_IB_valid[0] = 1;
      // dequeue outQueue[0]
      next_OB_valid[0] = 0;
      next_OB[0] = '1;
    end
  end else if (insert) begin
    next_size = curr_size + 1;
    if ((in_f_value < OB[0]) && (in_f_value < OB[1]) && (!IB_valid[0] || (in_f_value < IB[0]))) begin
      // enqueue directly into outQueue[0]
      next_OB[0] = in_f_value;
      next_OB_valid[0] = 1;
      // Bump outQueue[0] into inQueue[0]
      next_IB[0] = OB[0];
      next_IB_valid[0] = OB_valid[0];
    end else begin
      // enqueue into inQueue[0]
      next_IB[0] = in_f_value;
      next_IB_valid[0] = 1;
    end
  end else if (pop) begin
    next_size = curr_size - 1;
    next_OB_valid[0] = 0;
    next_OB[0] = '1;
  end

  // Calculate whether inQueue[j] < inQueue[j+1] or inQueue
  less_then_next_IB      = '0;
  less_then_same_OB     = '0;
  less_then_next_OB     = '0;
  less_then_next_next_OB = '0;

  for (j = 0; j < length; j += 1) begin
    // Special handle length at end of queue
    less_then_previous_IB[j]      = (j > 0        ) ? (IB[j] < IB[j-1] ) : !insert || (IB[j] <= in_f_value); // TODO needs to be less than or equals
    less_then_next_IB[j]      = (j < length-1) ? (IB[j] < IB[j+1] ) : 1;

    less_then_same_OB[j]     =                   (OB[j] < OB[j]  )    ;
    less_then_next_OB[j]     = (j < length-1) ? (OB[j] < OB[j+1]) : 1;
    less_then_next_next_OB[j] = (j < length-2) ? (OB[j] < OB[j+2]) : 1;
  end

  // Perform any additional sorting
  for (j = 0; j < length - 1; j += 1) begin
    if (less_then_same_OB[j] && less_then_next_OB[j] && less_then_previous_IB[j]) begin
      // Insert inQueue into empty outQueue slot
      next_OB[j] = IB[j];
      next_OB_valid[j] = IB_valid[j];
    end else if (less_then_next_OB[j] && less_then_next_IB[j] && less_then_next_next_OB[j]) begin
      // Swap inQueue and outQueue
      next_OB[j+1] = IB[j+1];
      next_OB_valid[j+1] = IB_valid[j+1];

      next_IB[j+1] = OB[j];
      next_IB_valid[j+1] = OB_valid[j];
    end else if ((j == length - 2) && !OB_valid[j+1] && IB_valid[j+1]) begin
      next_OB[j+1] = IB[j+1];
      next_OB_valid[j+1] = IB_valid[j+1];
    end else begin
      // Shift inQueue down
      next_IB[j+1] = IB[j];
      next_IB_valid[j+1] = IB_valid[j];
    end
  end

  // Shift outQueue length forward if there is a gap
  for (j = 0; j < length-1; j += 1) begin
    // TODO might not be necessary to check current OB_valid
    if (!OB_valid[j] && !next_OB_valid[j]) begin
      next_OB[j] = OB[j+1];
      next_OB_valid[j] = OB_valid[j+1];
      next_OB[j+1] = '1;
      next_OB_valid[j+1] = 0;
    end
  end
end

always_ff @(posedge clk) begin

  if (reset) begin
    curr_size  <= '0;
    IB_valid  <= '0;
    OB_valid  <= '0;

    for (i = 0; i < length; i += 1) begin
      IB[i]  <= '1;
      OB[i] <= '1;
    end

  end else begin
    curr_size  <= next_size;
    IB         <= next_IB;
    IB_valid   <= next_IB_valid;
    OB         <= next_OB;
    OB_valid   <= next_OB_valid;
  end
end

endmodule

systolic_array/tmp_open_list_queue_tb.sv
/* verilator lint_off UNUSEDSIGNAL */
module tmp_open_list_queue_tb;

  // Parameters
  parameter length = 8;
  parameter width = 32;

  // Inputs
  logic clk;
  logic reset;
  logic insert;
  logic pop;
  logic [width-1:0] in_f_value;

  // Outputs
  logic [width-1:0] out_f_value;
  logic empty;
  logic full;

  // Instantiate the Unit Under Test (UUT)
  tmp_open_list_queue #(
    .length(length),
    .width(width)
  ) uut (
    .clk(clk),
    .reset(reset),
    .insert(insert),
    .pop(pop),
    .in_f_value(in_f_value),
    .out_f_value(out_f_value),
    .empty(empty),
    .full(full)
  );

  // Clock generation
  initial begin
    clk = 0;
    reset = 1;
    forever #5 clk = ~clk; // 10ns period
  end

  // Test sequence
  initial begin
    // Initialize Inputs
    insert = 0;
    pop = 0;
    in_f_value = 0;

    $dumpfile("tmp_open_list_queue_tb.vcd");
    $dumpvars(0, tmp_open_list_queue_tb);

    // Wait for global reset
    @(posedge clk);
    reset = 0;

    // Insert fixed elements
    @(posedge clk);
    insert = 1;
    in_f_value = 32'd25;
    @(posedge clk);

    @(posedge clk);
    in_f_value = 32'd82;
    @(posedge clk);

    @(posedge clk);
    in_f_value = 32'd1;
    @(posedge clk);

    @(posedge clk);
    in_f_value = 32'd3;
    @(posedge clk);

    @(posedge clk);
    in_f_value = 32'd4;
    @(posedge clk);

    @(posedge clk);
    in_f_value = 32'd5;
    @(posedge clk);

    @(posedge clk);
    in_f_value = 32'd6;
    @(posedge clk);

    @(posedge clk);
    in_f_value = 32'd7;
    @(posedge clk);

    // this should not be inserted as the queue is full
    @(posedge clk);
    in_f_value = 32'd8;
    @(posedge clk);

    @(posedge clk);
    insert = 0;

    // Pop elements
    for (int i = 0; i < length; i++) begin
      @(posedge clk);
      pop = 1;
    end
    @(posedge clk);
    pop = 0;

    // Finish simulation
    repeat (2) @(posedge clk);
    $finish;
  end

  // Monitor outputs
  // initial begin
  //   $monitor("Time=%0t, insert=%b, pop=%b, in_data=%h, in_f_value=%h, out_data=%h, out_f_value=%h, empty=%b, full=%b",
  //            $time, insert, pop, in_data, in_f_value, out_data, out_f_value, empty, full);
  // end

endmodule

systolic_array/vivado_systolic_array/vivado_systolic_array.sim/sim_1/behav/xsim/tmp_open_list_queue_tb.vcd
$date
   Wed Sep  4 22:04:14 2024
$end

$version
  2024.1
  $dumpfile ("tmp_open_list_queue_tb.vcd") 
$end

$timescale
  1ps
$end

$scope module tmp_open_list_queue_tb $end
$var reg 1 ! clk $end
$var reg 1 " reset $end
$var reg 1 # insert $end
$var reg 1 $ pop $end
$var reg 32 % in_f_value [31:0] $end
$var reg 32 & out_f_value [31:0] $end
$var reg 1 ' empty $end
$var reg 1 ( full $end
$scope module uut $end
$var wire 1 ) clk $end
$var wire 1 * reset $end
$var wire 1 + insert $end
$var wire 1 , pop $end
$var wire 32 - in_f_value [31:0] $end
$var reg 32 & out_f_value [31:0] $end
$var reg 1 ( full $end
$var reg 1 ' empty $end
$var reg 5 . next_size [4:0] $end
$var reg 5 / curr_size [4:0] $end
$var reg 256 0 IB [255:0] $end
$var reg 256 1 next_IB [255:0] $end
$var reg 256 2 OB [255:0] $end
$var reg 256 3 next_OB [255:0] $end
$var reg 8 4 IB_valid [7:0] $end
$var reg 8 5 next_IB_valid [7:0] $end
$var reg 8 6 OB_valid [7:0] $end
$var reg 8 7 next_OB_valid [7:0] $end
$var reg 8 8 less_then_previous_IB [7:0] $end
$var reg 8 9 less_then_next_IB [7:0] $end
$var reg 8 : less_then_same_OB [7:0] $end
$var reg 8 ; less_then_next_OB [7:0] $end
$var reg 8 < less_then_next_next_OB [7:0] $end
$var integer 32 = i [31:0] $end
$var integer 32 > j [31:0] $end
$upscope $end
$scope begin Block99_4 $end
$var reg 32 ? i [31:0] $end
$upscope $end
$upscope $end
$enddefinitions $end

#0
$dumpvars
0!
1"
0#
0$
b0 %
bx &
x'
x(
0)
1*
0+
0,
b0 -
bx .
bx /
bx 0
bx11111111111111111111111111111111 1
bx 2
bx 3
bx 4
bx0 5
bx 6
bx 7
bx1 8
b1xxxxxxx 9
bx :
b1xxxxxxx ;
b11xxxxxx <
bx =
b111 >
b0 ?
$end

#5000
1!
0"
1)
0*
bx11111111111111111111111111111111 0
bx1111111111111111111111111111111111111111111111111111111111111111 1
bx0 4
bx00 5
b1xxxxxxx 9
bx :
b1xxxxxxx ;
b11xxxxxx <
b111 >

#10000
0!
0)

#15000
1!
1#
b11001 %
1)
1+
b11001 -
bx1111111111111111111111111111111111111111111111111111111111111111 0
bx111111111111111111111111111111111111111111111111111111111111111100000000000000000000000000011001 1
bx00 4
bx001 5
bx00 8
b1xxxxxx0 9
bx :
b1xxxxxxx ;
b11xxxxxx <
b111 >

#20000
0!
0)

#25000
1!
1)
bx111111111111111111111111111111111111111111111111111111111111111100000000000000000000000000011001 0
bx11111111111111111111111111111111111111111111111111111111111111110000000000000000000000000001100100000000000000000000000000011001 1
bx001 4
bx0011 5
bx001 8
b1xxxxx01 9
bx :
b1xxxxxxx ;
b11xxxxxx <
b111 >

#30000
0!
0)

#35000
1!
b1010010 %
1)
b1010010 -
bx11111111111111111111111111111111111111111111111111111111111111110000000000000000000000000001100100000000000000000000000000011001 0
bx1111111111111111111111111111111111111111111111111111111111111111000000000000000000000000000110010000000000000000000000000001100100000000000000000000000001010010 1
bx0011 4
bx00111 5
bx0001 8
b1xxxx010 9
bx :
b1xxxxxxx ;
b11xxxxxx <
b111 >

#40000
0!
0)

#45000
1!
1)
bx1111111111111111111111111111111111111111111111111111111111111111000000000000000000000000000110010000000000000000000000000001100100000000000000000000000001010010 0
bx111111111111111111111111111111111111111111111111111111111111111100000000000000000000000000011001000000000000000000000000000110010000000000000000000000000101001000000000000000000000000001010010 1
bx00111 4
bx001111 5
bx00011 8
b1xxx0100 9
bx :
b1xxxxxxx ;
b11xxxxxx <
b111 >

#50000
0!
0)

#55000
1!
b1 %
1)
b1 -
bx111111111111111111111111111111111111111111111111111111111111111100000000000000000000000000011001000000000000000000000000000110010000000000000000000000000101001000000000000000000000000001010010 0
bx11111111111111111111111111111111111111111111111111111111111111110000000000000000000000000001100100000000000000000000000000011001000000000000000000000000010100100000000000000000000000000101001000000000000000000000000000000001 1
bx001111 4
bx0011111 5
bx000100 8
b1xx01000 9
bx :
b1xxxxxxx ;
b11xxxxxx <
b111 >

#60000
0!
0)

#65000
1!
1)
bx11111111111111111111111111111111111111111111111111111111111111110000000000000000000000000001100100000000000000000000000000011001000000000000000000000000010100100000000000000000000000000101001000000000000000000000000000000001 0
b1111111111111111111111111111111111111111111111111111111111111111000000000000000000000000000110010000000000000000000000000001100100000000000000000000000001010010000000000000000000000000010100100000000000000000000000000000000100000000000000000000000000000001 1
bx0011111 4
b111111 5
bx0001001 8
b1x010001 9
bx :
b1xxxxxxx ;
b11xxxxxx <
b111 >

#70000
0!
0)

#75000
1!
b11 %
1)
b11 -
b1111111111111111111111111111111111111111111111111111111111111111000000000000000000000000000110010000000000000000000000000001100100000000000000000000000001010010000000000000000000000000010100100000000000000000000000000000000100000000000000000000000000000001 0
b1111111111111111111111111111111100000000000000000000000000011001000000000000000000000000000110010000000000000000000000000101001000000000000000000000000001010010000000000000000000000000000000010000000000000000000000000000000100000000000000000000000000000011 1
b111111 4
b1111111 5
b10001 8
b10100010 9
bx :
b1xxxxxxx ;
b11xxxxxx <
b111 >

#80000
0!
0)

#85000
1!
1)
b1111111111111111111111111111111100000000000000000000000000011001000000000000000000000000000110010000000000000000000000000101001000000000000000000000000001010010000000000000000000000000000000010000000000000000000000000000000100000000000000000000000000000011 0
b1100100000000000000000000000000011001000000000000000000000000010100100000000000000000000000000101001000000000000000000000000000000001000000000000000000000000000000010000000000000000000000000000001100000000000000000000000000000011 1
b1111111 4
b11111111 5
b100011 8
b11000100 9
bx :
b1xxxxxxx ;
b11xxxxxx <
b111 >

#90000
0!
0)

#95000
1!
b100 %
1)
b100 -
b1100100000000000000000000000000011001000000000000000000000000010100100000000000000000000000000101001000000000000000000000000000000001000000000000000000000000000000010000000000000000000000000000001100000000000000000000000000000011 0
b1100100000000000000000000000001010010000000000000000000000000010100100000000000000000000000000000000100000000000000000000000000000001000000000000000000000000000000110000000000000000000000000000001100000000000000000000000000000100 1
b11111111 4
b11111111 5
b1000101 8
b10001000 9
bx :
b1xxxxxxx ;
b11xxxxxx <
b111 >

#100000
0!
0)

#105000
1!
1)
b1100100000000000000000000000001010010000000000000000000000000010100100000000000000000000000000000000100000000000000000000000000000001000000000000000000000000000000110000000000000000000000000000001100000000000000000000000000000100 0
b101001000000000000000000000000001010010000000000000000000000000000000010000000000000000000000000000000100000000000000000000000000000011000000000000000000000000000000110000000000000000000000000000010000000000000000000000000000000100 1
b11111111 5
b10001011 8
b10010000 9
bx :
b1xxxxxxx ;
b11xxxxxx <
b111 >

#110000
0!
0)

#115000
1!
b101 %
1)
b101 -
b101001000000000000000000000000001010010000000000000000000000000000000010000000000000000000000000000000100000000000000000000000000000011000000000000000000000000000000110000000000000000000000000000010000000000000000000000000000000100 0
b101001000000000000000000000000000000001000000000000000000000000000000010000000000000000000000000000001100000000000000000000000000000011000000000000000000000000000001000000000000000000000000000000010000000000000000000000000000000101 1
b11111111 5
b10101 8
b10100000 9
bx :
b1xxxxxxx ;
b11xxxxxx <
b111 >

#120000
0!
0)

#125000
1!
1)
b101001000000000000000000000000000000001000000000000000000000000000000010000000000000000000000000000001100000000000000000000000000000011000000000000000000000000000001000000000000000000000000000000010000000000000000000000000000000101 0
b100000000000000000000000000000001000000000000000000000000000000110000000000000000000000000000001100000000000000000000000000000100000000000000000000000000000001000000000000000000000000000000010100000000000000000000000000000101 1
b11111111 5
b101011 8
b11000000 9
bx :
b1xxxxxxx ;
b11xxxxxx <
b111 >

#130000
0!
0)

#135000
1!
b110 %
1)
b110 -
b100000000000000000000000000000001000000000000000000000000000000110000000000000000000000000000001100000000000000000000000000000100000000000000000000000000000001000000000000000000000000000000010100000000000000000000000000000101 0
b100000000000000000000000000000011000000000000000000000000000000110000000000000000000000000000010000000000000000000000000000000100000000000000000000000000000001010000000000000000000000000000010100000000000000000000000000000110 1
b11111111 5
b1010101 8
b10000000 9
bx :
b1xxxxxxx ;
b11xxxxxx <
b111 >

#140000
0!
0)

#145000
1!
1)
b100000000000000000000000000000011000000000000000000000000000000110000000000000000000000000000010000000000000000000000000000000100000000000000000000000000000001010000000000000000000000000000010100000000000000000000000000000110 0
b1100000000000000000000000000000011000000000000000000000000000001000000000000000000000000000000010000000000000000000000000000000101000000000000000000000000000001010000000000000000000000000000011000000000000000000000000000000110 1
b11111111 5
b10101011 8
b10000000 9
bx :
b1xxxxxxx ;
b11xxxxxx <
b111 >

#150000
0!
0)

#155000
1!
b111 %
1)
b111 -
b1100000000000000000000000000000011000000000000000000000000000001000000000000000000000000000000010000000000000000000000000000000101000000000000000000000000000001010000000000000000000000000000011000000000000000000000000000000110 0
b1100000000000000000000000000000100000000000000000000000000000001000000000000000000000000000000010100000000000000000000000000000101000000000000000000000000000001100000000000000000000000000000011000000000000000000000000000000111 1
b11111111 5
b1010101 8
b10000000 9
bx :
b1xxxxxxx ;
b11xxxxxx <
b111 >

#160000
0!
0)

#165000
1!
1)
b1100000000000000000000000000000100000000000000000000000000000001000000000000000000000000000000010100000000000000000000000000000101000000000000000000000000000001100000000000000000000000000000011000000000000000000000000000000111 0
b10000000000000000000000000000000100000000000000000000000000000001010000000000000000000000000000010100000000000000000000000000000110000000000000000000000000000001100000000000000000000000000000011100000000000000000000000000000111 1
b11111111 5
b10101011 8
b10000000 9
bx :
b1xxxxxxx ;
b11xxxxxx <
b111 >

#170000
0!
0)

#175000
1!
b1000 %
1)
b1000 -
b10000000000000000000000000000000100000000000000000000000000000001010000000000000000000000000000010100000000000000000000000000000110000000000000000000000000000001100000000000000000000000000000011100000000000000000000000000000111 0
b10000000000000000000000000000000101000000000000000000000000000001010000000000000000000000000000011000000000000000000000000000000110000000000000000000000000000001110000000000000000000000000000011100000000000000000000000000001000 1
b11111111 5
b1010101 8
b10000000 9
bx :
b1xxxxxxx ;
b11xxxxxx <
b111 >

#180000
0!
0)

#185000
1!
1)
b10000000000000000000000000000000101000000000000000000000000000001010000000000000000000000000000011000000000000000000000000000000110000000000000000000000000000001110000000000000000000000000000011100000000000000000000000000001000 0
b10100000000000000000000000000000101000000000000000000000000000001100000000000000000000000000000011000000000000000000000000000000111000000000000000000000000000001110000000000000000000000000000100000000000000000000000000000001000 1
b11111111 5
b10101011 8
b10000000 9
bx :
b1xxxxxxx ;
b11xxxxxx <
b111 >

#190000
0!
0)

#195000
1!
0#
1)
0+
b10100000000000000000000000000000101000000000000000000000000000001100000000000000000000000000000011000000000000000000000000000000111000000000000000000000000000001110000000000000000000000000000100000000000000000000000000000001000 0
b10100000000000000000000000000000110000000000000000000000000000001100000000000000000000000000000011100000000000000000000000000000111000000000000000000000000000010000000000000000000000000000000100011111111111111111111111111111111 1
b11111110 5
b1010101 8
b10000000 9
bx :
b1xxxxxxx ;
b11xxxxxx <
b111 >

#200000
0!
0)

#205000
1!
1$
1)
1,
b10100000000000000000000000000000110000000000000000000000000000001100000000000000000000000000000011100000000000000000000000000000111000000000000000000000000000010000000000000000000000000000000100011111111111111111111111111111111 0
b11000000000000000000000000000000110000000000000000000000000000001110000000000000000000000000000011100000000000000000000000000001000000000000000000000000000000010001111111111111111111111111111111111111111111111111111111111111111 1
bx11111111111111111111111111111111 3
b11111110 4
b11111100 5
bx0 7
b10101011 8
b10000000 9
bx :
b1xxxxxxx ;
b11xxxxxx <
b111 >
b1 ?

#210000
0!
0)

#215000
1!
b11111111111111111111111111111111 &
1)
b11000000000000000000000000000000110000000000000000000000000000001110000000000000000000000000000011100000000000000000000000000001000000000000000000000000000000010001111111111111111111111111111111111111111111111111111111111111111 0
b11000000000000000000000000000000111000000000000000000000000000001110000000000000000000000000000100000000000000000000000000000001000111111111111111111111111111111111111111111111111111111111111111111111111111111111111111111111111 1
bx11111111111111111111111111111111 2
bx11111111111111111111111111111111xxxxxxxxxxxxxxxxxxxxxxxxxxxxxxxx 3
b11111100 4
b11111000 5
bx0 6
bx0x 7
b1010101 8
b10000000 9
bx0 :
b1xxxxxxx ;
b11xxxxxx <
b111 >
b10 ?

#220000
0!
0)

#225000
1!
bx &
1)
b11000000000000000000000000000000111000000000000000000000000000001110000000000000000000000000000100000000000000000000000000000001000111111111111111111111111111111111111111111111111111111111111111111111111111111111111111111111111 0
b11100000000000000000000000000000111000000000000000000000000000010000000000000000000000000000000100011111111111111111111111111111111111111111111111111111111111111111111111111111111111111111111111111111111111111111111111111111111 1
bx11111111111111111111111111111111xxxxxxxxxxxxxxxxxxxxxxxxxxxxxxxx 2
bx11111111111111111111111111111111xxxxxxxxxxxxxxxxxxxxxxxxxxxxxxxx11111111111111111111111111111111 3
b11111000 4
b11110000 5
bx0x 6
bx0x0 7
b10101001 8
b10000000 9
bx0x :
b1xxxxxxx ;
b11xxxxxx <
b111 >
b11 ?

#230000
0!
0)

#235000
1!
b11111111111111111111111111111111 &
1)
b11100000000000000000000000000000111000000000000000000000000000010000000000000000000000000000000100011111111111111111111111111111111111111111111111111111111111111111111111111111111111111111111111111111111111111111111111111111111 0
b11100000000000000000000000000001000000000000000000000000000000010001111111111111111111111111111111111111111111111111111111111111111111111111111111111111111111111111111111111111111111111111111111111111111111111111111111111111111 1
bx11111111111111111111111111111111xxxxxxxxxxxxxxxxxxxxxxxxxxxxxxxx11111111111111111111111111111111 2
bx11111111111111111111111111111111xxxxxxxxxxxxxxxxxxxxxxxxxxxxxxxx11111111111111111111111111111111xxxxxxxxxxxxxxxxxxxxxxxxxxxxxxxx 3
b11110000 4
b11100000 5
bx0x0 6
bx0x0x 7
b1010001 8
b10000000 9
bx0x0 :
b1xxxxxxx ;
b11xxxxx0 <
b111 >
b100 ?

#240000
0!
0)

#245000
1!
bx &
1)
b11100000000000000000000000000001000000000000000000000000000000010001111111111111111111111111111111111111111111111111111111111111111111111111111111111111111111111111111111111111111111111111111111111111111111111111111111111111111 0
b100000000000000000000000000000001000111111111111111111111111111111111111111111111111111111111111111111111111111111111111111111111111111111111111111111111111111111111111111111111111111111111111111111111111111111111111111111111111 1
bx11111111111111111111111111111111xxxxxxxxxxxxxxxxxxxxxxxxxxxxxxxx11111111111111111111111111111111xxxxxxxxxxxxxxxxxxxxxxxxxxxxxxxx 2
bx11111111111111111111111111111111xxxxxxxxxxxxxxxxxxxxxxxxxxxxxxxx11111111111111111111111111111111xxxxxxxxxxxxxxxxxxxxxxxxxxxxxxxx11111111111111111111111111111111 3
b11100000 4
b11000000 5
bx0x0x 6
bx0x0x0 7
b10100001 8
b10000000 9
bx0x0x :
b1xxxxxxx ;
b11xxxx0x <
b111 >
b101 ?

#250000
0!
0)

#255000
1!
b11111111111111111111111111111111 &
1)
b100000000000000000000000000000001000111111111111111111111111111111111111111111111111111111111111111111111111111111111111111111111111111111111111111111111111111111111111111111111111111111111111111111111111111111111111111111111111 0
b100011111111111111111111111111111111111111111111111111111111111111111111111111111111111111111111111111111111111111111111111111111111111111111111111111111111111111111111111111111111111111111111111111111111111111111111111111111111 1
bx11111111111111111111111111111111xxxxxxxxxxxxxxxxxxxxxxxxxxxxxxxx11111111111111111111111111111111xxxxxxxxxxxxxxxxxxxxxxxxxxxxxxxx11111111111111111111111111111111 2
bx11111111111111111111111111111111xxxxxxxxxxxxxxxxxxxxxxxxxxxxxxxx11111111111111111111111111111111xxxxxxxxxxxxxxxxxxxxxxxxxxxxxxxx11111111111111111111111111111111xxxxxxxxxxxxxxxxxxxxxxxxxxxxxxxx 3
b11000000 4
b10000000 5
bx0x0x0 6
bx0x0x0x 7
b1000001 8
b10000000 9
bx0x0x0 :
b1xxxxxxx ;
b11xxx0x0 <
b111 >
b110 ?

#260000
0!
0)

#265000
1!
bx &
1)
b100011111111111111111111111111111111111111111111111111111111111111111111111111111111111111111111111111111111111111111111111111111111111111111111111111111111111111111111111111111111111111111111111111111111111111111111111111111111 0
b1111111111111111111111111111111111111111111111111111111111111111111111111111111111111111111111111111111111111111111111111111111111111111111111111111111111111111111111111111111111111111111111111111111111111111111111111111111111111111111111111111111111111111 1
bx11111111111111111111111111111111xxxxxxxxxxxxxxxxxxxxxxxxxxxxxxxx11111111111111111111111111111111xxxxxxxxxxxxxxxxxxxxxxxxxxxxxxxx11111111111111111111111111111111xxxxxxxxxxxxxxxxxxxxxxxxxxxxxxxx 2
bx11111111111111111111111111111111xxxxxxxxxxxxxxxxxxxxxxxxxxxxxxxx11111111111111111111111111111111xxxxxxxxxxxxxxxxxxxxxxxxxxxxxxxx11111111111111111111111111111111xxxxxxxxxxxxxxxxxxxxxxxxxxxxxxxx11111111111111111111111111111111 3
b10000000 4
b0 5
bx0x0x0x 6
bx0x0x0x0 7
b10000001 8
b10000000 9
bx0x0x0x :
b1xxxxxxx ;
b11xx0x0x <
b111 >
b111 ?

#270000
0!
0)

#275000
1!
b11111111111111111111111111111111 &
1)
b1111111111111111111111111111111111111111111111111111111111111111111111111111111111111111111111111111111111111111111111111111111111111111111111111111111111111111111111111111111111111111111111111111111111111111111111111111111111111111111111111111111111111111 0
bx11111111111111111111111111111111xxxxxxxxxxxxxxxxxxxxxxxxxxxxxxxx11111111111111111111111111111111xxxxxxxxxxxxxxxxxxxxxxxxxxxxxxxx11111111111111111111111111111111xxxxxxxxxxxxxxxxxxxxxxxxxxxxxxxx11111111111111111111111111111111 2
b11111111111111111111111111111111xxxxxxxxxxxxxxxxxxxxxxxxxxxxxxxx11111111111111111111111111111111xxxxxxxxxxxxxxxxxxxxxxxxxxxxxxxx11111111111111111111111111111111xxxxxxxxxxxxxxxxxxxxxxxxxxxxxxxx11111111111111111111111111111111xxxxxxxxxxxxxxxxxxxxxxxxxxxxxxxx 3
b0 4
bx0x0x0x0 6
b0x0x0x0x 7
b1 8
b10000000 9
bx0x0x0x0 :
b1xxxxxxx ;
b11x0x0x0 <
b111 >
b1000 ?

#280000
0!
0)

#285000
1!
0$
bx &
1)
0,
b11111111111111111111111111111111xxxxxxxxxxxxxxxxxxxxxxxxxxxxxxxx11111111111111111111111111111111xxxxxxxxxxxxxxxxxxxxxxxxxxxxxxxx11111111111111111111111111111111xxxxxxxxxxxxxxxxxxxxxxxxxxxxxxxx11111111111111111111111111111111xxxxxxxxxxxxxxxxxxxxxxxxxxxxxxxx 2
b1111111111111111111111111111111111111111111111111111111111111111xxxxxxxxxxxxxxxxxxxxxxxxxxxxxxxx11111111111111111111111111111111xxxxxxxxxxxxxxxxxxxxxxxxxxxxxxxx11111111111111111111111111111111xxxxxxxxxxxxxxxxxxxxxxxxxxxxxxxxxxxxxxxxxxxxxxxxxxxxxxxxxxxxxxxx 3
b0x0x0x0x 6
b0x0x0xx 7
b10000000 9
b0x0x0x0x :
b1xxxxxxx ;
b110x0x0x <
b111 >

#290000
0!
0)

#295000
1!
1)
b1111111111111111111111111111111111111111111111111111111111111111xxxxxxxxxxxxxxxxxxxxxxxxxxxxxxxx11111111111111111111111111111111xxxxxxxxxxxxxxxxxxxxxxxxxxxxxxxx11111111111111111111111111111111xxxxxxxxxxxxxxxxxxxxxxxxxxxxxxxxxxxxxxxxxxxxxxxxxxxxxxxxxxxxxxxx 2
b111111111111111111111111111111111111111111111111111111111111111111111111111111111111111111111111xxxxxxxxxxxxxxxxxxxxxxxxxxxxxxxx11111111111111111111111111111111xxxxxxxxxxxxxxxxxxxxxxxxxxxxxxxxxxxxxxxxxxxxxxxxxxxxxxxxxxxxxxxxxxxxxxxxxxxxxxxxxxxxxxxxxxxxxxxx 3
b0x0x0xx 6
b0x0xxx 7
b10000000 9
b0x0x0xx :
b10xxxxxx ;
b11x0x0xx <
b111 >

